git_adr/__init__.py
git_adr/cli.py
git_adr/hooks.py
git_adr/py.typed
git_adr/ai/__init__.py
git_adr/ai/service.py
git_adr/commands/__init__.py
git_adr/commands/_editor.py
git_adr/commands/_shared.py
git_adr/commands/ai_ask.py
git_adr/commands/ai_draft.py
git_adr/commands/ai_suggest.py
git_adr/commands/ai_summarize.py
git_adr/commands/artifact_get.py
git_adr/commands/artifact_rm.py
git_adr/commands/artifacts.py
git_adr/commands/attach.py
git_adr/commands/ci.py
git_adr/commands/config.py
git_adr/commands/convert.py
git_adr/commands/edit.py
git_adr/commands/export.py
git_adr/commands/hook.py
git_adr/commands/hooks_cli.py
git_adr/commands/import_.py
git_adr/commands/init.py
git_adr/commands/issue.py
git_adr/commands/link.py
git_adr/commands/list.py
git_adr/commands/log.py
git_adr/commands/metrics.py
git_adr/commands/new.py
git_adr/commands/onboard.py
git_adr/commands/report.py
git_adr/commands/rm.py
git_adr/commands/search.py
git_adr/commands/show.py
git_adr/commands/stats.py
git_adr/commands/supersede.py
git_adr/commands/sync.py
git_adr/commands/templates_cli.py
git_adr/commands/wiki_init.py
git_adr/commands/wiki_sync.py
git_adr/core/__init__.py
git_adr/core/adr.py
git_adr/core/config.py
git_adr/core/gh_client.py
git_adr/core/git.py
git_adr/core/index.py
git_adr/core/issue.py
git_adr/core/issue_template.py
git_adr/core/notes.py
git_adr/core/templates.py
git_adr/core/utils.py
git_adr/formats/__init__.py
git_adr/templates/__init__.py
git_adr/templates/ci/github-actions-sync.yml.j2
git_adr/templates/ci/github-actions-validate.yml.j2
git_adr/templates/ci/gitlab-ci-sync.yml.j2
git_adr/templates/governance/codeowners.j2
git_adr/templates/governance/issue-template-adr.md.j2
git_adr/templates/governance/pr-template.md.j2
git_adr/templates/issues/bug_report.md
git_adr/templates/issues/documentation.md
git_adr/templates/issues/feature_request.md
git_adr/wiki/__init__.py
git_adr/wiki/service.py
git_adr-0.3.0.dist-info/METADATA
git_adr-0.3.0.dist-info/WHEEL
git_adr-0.3.0.dist-info/entry_points.txt
git_adr-0.3.0.dist-info/licenses/LICENSE
git_adr-0.3.0.dist-info/RECORD
