Metadata-Version: 2.4
Name: git-adr
Version: 0.3.0
Summary: Architecture Decision Records management for git repositories using git notes
Project-URL: Homepage, https://github.com/zircote/git-adr
Project-URL: Documentation, https://github.com/zircote/git-adr#readme
Project-URL: Repository, https://github.com/zircote/git-adr.git
Project-URL: Issues, https://github.com/zircote/git-adr/issues
Author: zircote
License: MIT
License-File: LICENSE
Keywords: adr,architecture,decision,documentation,git,git-notes,records
Classifier: Development Status :: 3 - Alpha
Classifier: Environment :: Console
Classifier: Intended Audience :: Developers
Classifier: License :: OSI Approved :: MIT License
Classifier: Operating System :: OS Independent
Classifier: Programming Language :: Python :: 3
Classifier: Programming Language :: Python :: 3.11
Classifier: Programming Language :: Python :: 3.12
Classifier: Programming Language :: Python :: 3.13
Classifier: Topic :: Software Development :: Documentation
Classifier: Topic :: Software Development :: Version Control :: Git
Classifier: Typing :: Typed
Requires-Python: >=3.11
Requires-Dist: jinja2>=3.1.0
Requires-Dist: mistune>=3.0.0
Requires-Dist: python-frontmatter>=1.0.0
Requires-Dist: pyyaml>=6.0.0
Requires-Dist: rich>=13.0.0
Requires-Dist: typer>=0.9.0
Provides-Extra: ai
Requires-Dist: langchain-anthropic>=0.2.0; extra == 'ai'
Requires-Dist: langchain-core>=0.3.0; extra == 'ai'
Requires-Dist: langchain-google-genai>=2.0.0; extra == 'ai'
Requires-Dist: langchain-ollama>=0.2.0; extra == 'ai'
Requires-Dist: langchain-openai>=0.2.0; extra == 'ai'
Provides-Extra: all
Requires-Dist: langchain-anthropic>=0.2.0; extra == 'all'
Requires-Dist: langchain-core>=0.3.0; extra == 'all'
Requires-Dist: langchain-google-genai>=2.0.0; extra == 'all'
Requires-Dist: langchain-ollama>=0.2.0; extra == 'all'
Requires-Dist: langchain-openai>=0.2.0; extra == 'all'
Requires-Dist: pygithub>=2.0.0; extra == 'all'
Requires-Dist: python-docx>=1.0.0; extra == 'all'
Requires-Dist: python-gitlab>=4.0.0; extra == 'all'
Provides-Extra: dev
Requires-Dist: bandit>=1.7.0; extra == 'dev'
Requires-Dist: mypy>=1.13.0; extra == 'dev'
Requires-Dist: pip-audit>=2.7.0; extra == 'dev'
Requires-Dist: pytest-asyncio>=0.24.0; extra == 'dev'
Requires-Dist: pytest-cov>=5.0.0; extra == 'dev'
Requires-Dist: pytest>=8.0.0; extra == 'dev'
Requires-Dist: ruff>=0.8.0; extra == 'dev'
Requires-Dist: types-pyyaml>=6.0.0; extra == 'dev'
Provides-Extra: export
Requires-Dist: python-docx>=1.0.0; extra == 'export'
Provides-Extra: wiki
Requires-Dist: pygithub>=2.0.0; extra == 'wiki'
Requires-Dist: python-gitlab>=4.0.0; extra == 'wiki'
